garden/__init__.py
garden/decorator.py
garden/garden.py
garden/middleware.py
garden/util.py
garden/middlewares/__init__.py
garden/middlewares/mongo.py
garden/middlewares/redis.py
garden/middlewares/selenium.py
garden/middlewares/state.py
garden/mixins/__init__.py
garden/mixins/debug.py
garden/mixins/log.py
garden/mixins/queue.py
garden-1.0.0b1.dist-info/METADATA
garden-1.0.0b1.dist-info/WHEEL
garden-1.0.0b1.dist-info/licenses/LICENSE
garden-1.0.0b1.dist-info/RECORD
