Metadata-Version: 2.4
Name: garden
Version: 1.0.0b1
Summary: Garden is a simple asynchronous task management library for Python.
Project-URL: Homepage, https://github.com/pulsgarney/garden
Project-URL: Documentation, https://pulsgarney.github.io/garden
Project-URL: Repository, https://github.com/pulsgarney/garden
Project-URL: Changelog, https://pulsgarney.github.io/garden/changelog
Author-email: Puls Garney <me@pulsgarney.com>
Maintainer-email: Puls Garney <me@pulsgarney.com>
License-Expression: GPL-3.0
License-File: LICENSE
Keywords: asynchronous,asyncio compatible,background tasks,concurrency,job queue,parallel processing,productivity tools,python library,task management
Classifier: Development Status :: 4 - Beta
Classifier: Framework :: AsyncIO
Classifier: Intended Audience :: Developers
Classifier: License :: OSI Approved :: GNU General Public License v3 (GPLv3)
Classifier: Operating System :: OS Independent
Classifier: Programming Language :: Python :: 3
Classifier: Programming Language :: Python :: 3 :: Only
Classifier: Programming Language :: Python :: 3.10
Classifier: Programming Language :: Python :: 3.11
Classifier: Programming Language :: Python :: 3.12
Classifier: Programming Language :: Python :: 3.13
Classifier: Programming Language :: Python :: 3.14
Classifier: Topic :: Software Development :: Libraries
Classifier: Topic :: Software Development :: Libraries :: Python Modules
Classifier: Topic :: Utilities
Classifier: Typing :: Typed
Requires-Python: >=3.10
Requires-Dist: packaging>=21.0
Provides-Extra: all
Provides-Extra: db
